raws.py
rawscli-0.9.7.dist-info/LICENSE
rawscli-0.9.7.dist-info/METADATA
rawscli-0.9.7.dist-info/WHEEL
rawscli-0.9.7.dist-info/entry_points.txt
rawscli-0.9.7.dist-info/top_level.txt
rawscli-0.9.7.dist-info/RECORD
