Metadata-Version: 2.1
Name: rawscli
Version: 0.9.7
Summary: A simple tool to manage your AWS credentials
Home-page: https://github.com/andzhi4/raws
Author: Viacheslav Andzhich
Author-email: va.public@protonmail.com
License: MIT
Classifier: License :: OSI Approved :: MIT License
Classifier: Programming Language :: Python :: 3
Classifier: Programming Language :: Python :: 3 :: Only
Classifier: Programming Language :: Python :: Implementation :: CPython
Classifier: Programming Language :: Python :: Implementation :: PyPy
Requires-Python: >=3.9
License-File: LICENSE
Requires-Dist: pyperclip ==1.8.2
